{
  "annotations": {
    "list": [
      {
        "builtIn": 1,
        "datasource": {
          "type": "grafana",
          "uid": "-- Grafana --"
        },
        "enable": true,
        "hide": true,
        "iconColor": "rgba(0, 211, 255, 1)",
        "name": "Annotations & Alerts",
        "target": {
          "limit": 100,
          "matchAny": false,
          "tags": [],
          "type": "dashboard"
        },
        "type": "dashboard"
      }
    ]
  },
  "editable": true,
  "fiscalYearStartMonth": 0,
  "graphTooltip": 1,
  "id": 2,
  "links": [],
  "liveNow": false,
  "panels": [
    {
      "datasource": "Prometheus",
      "fieldConfig": {
        "defaults": {
          "color": {
            "mode": "thresholds"
          },
          "mappings": [],
          "thresholds": {
            "mode": "absolute",
            "steps": [
              {
                "color": "green",
                "value": null
              },
              {
                "color": "red",
                "value": 1
              }
            ]
          }
        },
        "overrides": []
      },
      "gridPos": {
        "h": 3,
        "w": 3,
        "x": 0,
        "y": 0
      },
      "id": 10,
      "options": {
        "colorMode": "value",
        "graphMode": "area",
        "justifyMode": "auto",
        "orientation": "auto",
        "reduceOptions": {
          "calcs": [
            "lastNotNull"
          ],
          "fields": "",
          "values": false
        },
        "textMode": "auto"
      },
      "pluginVersion": "9.5.2",
      "targets": [
        {
          "datasource": "Prometheus",
          "editorMode": "code",
          "expr": "node_load1",
          "legendFormat": "__auto",
          "range": true,
          "refId": "A"
        }
      ],
      "title": "Load 1m",
      "type": "stat"
    },
    {
      "datasource": "Prometheus",
      "fieldConfig": {
        "defaults": {
          "color": {
            "mode": "thresholds"
          },
          "mappings": [],
          "thresholds": {
            "mode": "absolute",
            "steps": [
              {
                "color": "green",
                "value": null
              },
              {
                "color": "red",
                "value": 1
              }
            ]
          }
        },
        "overrides": []
      },
      "gridPos": {
        "h": 3,
        "w": 3,
        "x": 3,
        "y": 0
      },
      "id": 6,
      "options": {
        "colorMode": "value",
        "graphMode": "area",
        "justifyMode": "auto",
        "orientation": "auto",
        "reduceOptions": {
          "calcs": [
            "lastNotNull"
          ],
          "fields": "",
          "values": false
        },
        "textMode": "auto"
      },
      "pluginVersion": "9.5.2",
      "targets": [
        {
          "datasource": "Prometheus",
          "editorMode": "code",
          "expr": "node_load5",
          "legendFormat": "__auto",
          "range": true,
          "refId": "A"
        }
      ],
      "title": "Load 5m",
      "type": "stat"
    },
    {
      "datasource": "Prometheus",
      "fieldConfig": {
        "defaults": {
          "color": {
            "mode": "thresholds"
          },
          "mappings": [],
          "thresholds": {
            "mode": "absolute",
            "steps": [
              {
                "color": "green",
                "value": null
              },
              {
                "color": "red",
                "value": 1
              }
            ]
          }
        },
        "overrides": []
      },
      "gridPos": {
        "h": 3,
        "w": 3,
        "x": 6,
        "y": 0
      },
      "id": 8,
      "options": {
        "colorMode": "value",
        "graphMode": "area",
        "justifyMode": "auto",
        "orientation": "auto",
        "reduceOptions": {
          "calcs": [
            "lastNotNull"
          ],
          "fields": "",
          "values": false
        },
        "textMode": "auto"
      },
      "pluginVersion": "9.5.2",
      "targets": [
        {
          "datasource": "Prometheus",
          "editorMode": "code",
          "expr": "node_load15",
          "legendFormat": "__auto",
          "range": true,
          "refId": "A"
        }
      ],
      "title": "Load 15m",
      "type": "stat"
    },
    {
      "datasource": "Prometheus",
      "fieldConfig": {
        "defaults": {
          "color": {
            "mode": "thresholds"
          },
          "mappings": [],
          "thresholds": {
            "mode": "absolute",
            "steps": [
              {
                "color": "green",
                "value": null
              },
              {
                "color": "red",
                "value": 1
              }
            ]
          }
        },
        "overrides": []
      },
      "gridPos": {
        "h": 3,
        "w": 3,
        "x": 9,
        "y": 0
      },
      "id": 212,
      "options": {
        "colorMode": "value",
        "graphMode": "area",
        "justifyMode": "auto",
        "orientation": "auto",
        "reduceOptions": {
          "calcs": [
            "lastNotNull"
          ],
          "fields": "",
          "values": false
        },
        "textMode": "auto"
      },
      "pluginVersion": "9.5.2",
      "targets": [
        {
          "datasource": "Prometheus",
          "editorMode": "code",
          "expr": "node_vmstat_oom_kill",
          "legendFormat": "__auto",
          "range": true,
          "refId": "A"
        }
      ],
      "title": "OOM Killed",
      "type": "stat"
    },
    {
      "datasource": "Prometheus",
      "fieldConfig": {
        "defaults": {
          "color": {
            "mode": "thresholds"
          },
          "mappings": [],
          "thresholds": {
            "mode": "absolute",
            "steps": [
              {
                "color": "text",
                "value": null
              }
            ]
          }
        },
        "overrides": []
      },
      "gridPos": {
        "h": 3,
        "w": 2,
        "x": 13,
        "y": 0
      },
      "id": 14,
      "options": {
        "colorMode": "value",
        "graphMode": "none",
        "justifyMode": "auto",
        "orientation": "auto",
        "reduceOptions": {
          "calcs": [
            "lastNotNull"
          ],
          "fields": "",
          "values": false
        },
        "textMode": "auto"
      },
      "pluginVersion": "9.5.2",
      "targets": [
        {
          "datasource": "Prometheus",
          "editorMode": "code",
          "expr": "count(count(node_cpu_seconds_total) by (cpu))",
          "legendFormat": "__auto",
          "range": true,
          "refId": "A"
        }
      ],
      "title": "CPU Cores",
      "type": "stat"
    },
    {
      "datasource": "Prometheus",
      "fieldConfig": {
        "defaults": {
          "color": {
            "mode": "thresholds"
          },
          "decimals": 0,
          "mappings": [],
          "thresholds": {
            "mode": "absolute",
            "steps": [
              {
                "color": "text",
                "value": null
              }
            ]
          },
          "unit": "bytes"
        },
        "overrides": []
      },
      "gridPos": {
        "h": 3,
        "w": 2,
        "x": 15,
        "y": 0
      },
      "id": 16,
      "options": {
        "colorMode": "value",
        "graphMode": "none",
        "justifyMode": "auto",
        "orientation": "auto",
        "reduceOptions": {
          "calcs": [
            "lastNotNull"
          ],
          "fields": "",
          "values": false
        },
        "textMode": "auto"
      },
      "pluginVersion": "9.5.2",
      "targets": [
        {
          "datasource": "Prometheus",
          "editorMode": "code",
          "expr": "node_memory_MemTotal_bytes",
          "legendFormat": "__auto",
          "range": true,
          "refId": "A"
        }
      ],
      "title": "Memory Total",
      "type": "stat"
    },
    {
      "datasource": "Prometheus",
      "fieldConfig": {
        "defaults": {
          "color": {
            "mode": "thresholds"
          },
          "decimals": 0,
          "mappings": [],
          "thresholds": {
            "mode": "absolute",
            "steps": [
              {
                "color": "text",
                "value": null
              }
            ]
          },
          "unit": "bytes"
        },
        "overrides": []
      },
      "gridPos": {
        "h": 3,
        "w": 2,
        "x": 17,
        "y": 0
      },
      "id": 18,
      "options": {
        "colorMode": "value",
        "graphMode": "none",
        "justifyMode": "auto",
        "orientation": "auto",
        "reduceOptions": {
          "calcs": [
            "lastNotNull"
          ],
          "fields": "",
          "values": false
        },
        "textMode": "auto"
      },
      "pluginVersion": "9.5.2",
      "targets": [
        {
          "datasource": "Prometheus",
          "editorMode": "code",
          "expr": "node_memory_SwapTotal_bytes",
          "legendFormat": "__auto",
          "range": true,
          "refId": "A"
        }
      ],
      "title": "Swap Total",
      "type": "stat"
    },
    {
      "datasource": "Prometheus",
      "fieldConfig": {
        "defaults": {
          "color": {
            "mode": "thresholds"
          },
          "mappings": [],
          "thresholds": {
            "mode": "absolute",
            "steps": [
              {
                "color": "text",
                "value": null
              }
            ]
          },
          "unit": "bytes"
        },
        "overrides": []
      },
      "gridPos": {
        "h": 3,
        "w": 2,
        "x": 19,
        "y": 0
      },
      "id": 61,
      "options": {
        "colorMode": "value",
        "graphMode": "none",
        "justifyMode": "auto",
        "orientation": "auto",
        "reduceOptions": {
          "calcs": [
            "lastNotNull"
          ],
          "fields": "",
          "values": false
        },
        "textMode": "auto"
      },
      "pluginVersion": "9.5.2",
      "targets": [
        {
          "datasource": "Prometheus",
          "editorMode": "code",
          "expr": "node_filesystem_size_bytes{mountpoint=\"/\"}",
          "legendFormat": "__auto",
          "range": true,
          "refId": "A"
        }
      ],
      "title": "RootFS",
      "type": "stat"
    },
    {
      "datasource": "Prometheus",
      "fieldConfig": {
        "defaults": {
          "color": {
            "mode": "thresholds"
          },
          "mappings": [],
          "thresholds": {
            "mode": "absolute",
            "steps": [
              {
                "color": "blue",
                "value": null
              }
            ]
          },
          "unit": "s"
        },
        "overrides": []
      },
      "gridPos": {
        "h": 3,
        "w": 2,
        "x": 22,
        "y": 0
      },
      "id": 12,
      "options": {
        "colorMode": "value",
        "graphMode": "none",
        "justifyMode": "auto",
        "orientation": "auto",
        "reduceOptions": {
          "calcs": [
            "lastNotNull"
          ],
          "fields": "",
          "values": false
        },
        "textMode": "auto"
      },
      "pluginVersion": "9.5.2",
      "targets": [
        {
          "datasource": "Prometheus",
          "editorMode": "code",
          "expr": "node_time_seconds - node_boot_time_seconds",
          "legendFormat": "__auto",
          "range": true,
          "refId": "A"
        }
      ],
      "title": "uptime",
      "type": "stat"
    },
    {
      "datasource": "Prometheus",
      "fieldConfig": {
        "defaults": {
          "color": {
            "mode": "thresholds"
          },
          "decimals": 0,
          "mappings": [],
          "max": 1,
          "thresholds": {
            "mode": "absolute",
            "steps": [
              {
                "color": "green",
                "value": null
              },
              {
                "color": "#EAB839",
                "value": 0.5
              },
              {
                "color": "red",
                "value": 0.8
              }
            ]
          },
          "unit": "percentunit"
        },
        "overrides": []
      },
      "gridPos": {
        "h": 12,
        "w": 24,
        "x": 0,
        "y": 3
      },
      "id": 4,
      "options": {
        "displayMode": "lcd",
        "minVizHeight": 10,
        "minVizWidth": 0,
        "orientation": "horizontal",
        "reduceOptions": {
          "calcs": [
            "lastNotNull"
          ],
          "fields": "",
          "values": false
        },
        "showUnfilled": true,
        "valueMode": "color"
      },
      "pluginVersion": "9.5.2",
      "targets": [
        {
          "datasource": "Prometheus",
          "editorMode": "code",
          "expr": "sum(irate(node_cpu_seconds_total{mode!=\"idle\"}[1m])) by (cpu)",
          "legendFormat": "__auto",
          "range": true,
          "refId": "A"
        }
      ],
      "title": "CPU Usage per cores",
      "transformations": [],
      "type": "bargauge"
    },
    {
      "datasource": "Prometheus",
      "fieldConfig": {
        "defaults": {
          "color": {
            "mode": "palette-classic"
          },
          "custom": {
            "axisCenteredZero": false,
            "axisColorMode": "text",
            "axisLabel": "",
            "axisPlacement": "auto",
            "barAlignment": 0,
            "drawStyle": "line",
            "fillOpacity": 0,
            "gradientMode": "none",
            "hideFrom": {
              "legend": false,
              "tooltip": false,
              "viz": false
            },
            "lineInterpolation": "smooth",
            "lineWidth": 1,
            "pointSize": 5,
            "scaleDistribution": {
              "type": "linear"
            },
            "showPoints": "auto",
            "spanNulls": false,
            "stacking": {
              "group": "A",
              "mode": "none"
            },
            "thresholdsStyle": {
              "mode": "off"
            }
          },
          "mappings": [],
          "max": 6499999999,
          "thresholds": {
            "mode": "absolute",
            "steps": [
              {
                "color": "green",
                "value": null
              },
              {
                "color": "#EAB839",
                "value": 4000000000
              }
            ]
          },
          "unit": "rothz"
        },
        "overrides": []
      },
      "gridPos": {
        "h": 8,
        "w": 12,
        "x": 0,
        "y": 15
      },
      "id": 235,
      "options": {
        "legend": {
          "calcs": [],
          "displayMode": "list",
          "placement": "bottom",
          "showLegend": true
        },
        "tooltip": {
          "mode": "single",
          "sort": "none"
        }
      },
      "pluginVersion": "9.3.2",
      "targets": [
        {
          "datasource": "Prometheus",
          "editorMode": "code",
          "expr": "sum(node_cpu_scaling_frequency_hertz) by (cpu)",
          "legendFormat": "__auto",
          "range": true,
          "refId": "A"
        }
      ],
      "title": "CPU Clock",
      "type": "timeseries"
    },
    {
      "datasource": {
        "type": "prometheus",
        "uid": "PBFA97CFB590B2093"
      },
      "fieldConfig": {
        "defaults": {
          "color": {
            "mode": "palette-classic"
          },
          "custom": {
            "axisCenteredZero": false,
            "axisColorMode": "text",
            "axisLabel": "",
            "axisPlacement": "auto",
            "barAlignment": 0,
            "drawStyle": "line",
            "fillOpacity": 0,
            "gradientMode": "none",
            "hideFrom": {
              "legend": false,
              "tooltip": false,
              "viz": false
            },
            "lineInterpolation": "smooth",
            "lineWidth": 1,
            "pointSize": 5,
            "scaleDistribution": {
              "type": "linear"
            },
            "showPoints": "auto",
            "spanNulls": false,
            "stacking": {
              "group": "A",
              "mode": "none"
            },
            "thresholdsStyle": {
              "mode": "off"
            }
          },
          "mappings": [],
          "thresholds": {
            "mode": "absolute",
            "steps": [
              {
                "color": "green",
                "value": null
              },
              {
                "color": "red",
                "value": 80
              }
            ]
          },
          "unit": "celsius"
        },
        "overrides": []
      },
      "gridPos": {
        "h": 8,
        "w": 12,
        "x": 12,
        "y": 15
      },
      "id": 237,
      "options": {
        "legend": {
          "calcs": [],
          "displayMode": "list",
          "placement": "bottom",
          "showLegend": true
        },
        "tooltip": {
          "mode": "single",
          "sort": "none"
        }
      },
      "targets": [
        {
          "datasource": "Prometheus",
          "editorMode": "code",
          "expr": "sum(node_hwmon_temp_celsius * on(chip) group_left(chip_name) node_hwmon_chip_names{chip_name=\"k10temp\"}) by (sensor, chip_name)",
          "legendFormat": "__auto",
          "range": true,
          "refId": "A"
        }
      ],
      "title": "CPU Temp",
      "type": "timeseries"
    },
    {
      "datasource": "Prometheus",
      "fieldConfig": {
        "defaults": {
          "color": {
            "mode": "palette-classic"
          },
          "custom": {
            "axisCenteredZero": false,
            "axisColorMode": "text",
            "axisLabel": "",
            "axisPlacement": "auto",
            "barAlignment": 0,
            "drawStyle": "line",
            "fillOpacity": 0,
            "gradientMode": "none",
            "hideFrom": {
              "legend": false,
              "tooltip": false,
              "viz": false
            },
            "lineInterpolation": "linear",
            "lineWidth": 1,
            "pointSize": 5,
            "scaleDistribution": {
              "type": "linear"
            },
            "showPoints": "auto",
            "spanNulls": false,
            "stacking": {
              "group": "A",
              "mode": "none"
            },
            "thresholdsStyle": {
              "mode": "off"
            }
          },
          "mappings": [],
          "max": 1,
          "min": 0,
          "thresholds": {
            "mode": "absolute",
            "steps": [
              {
                "color": "green",
                "value": null
              },
              {
                "color": "red",
                "value": 80
              }
            ]
          },
          "unit": "percentunit"
        },
        "overrides": []
      },
      "gridPos": {
        "h": 9,
        "w": 12,
        "x": 0,
        "y": 23
      },
      "id": 2,
      "options": {
        "legend": {
          "calcs": [],
          "displayMode": "list",
          "placement": "bottom",
          "showLegend": true
        },
        "tooltip": {
          "mode": "single",
          "sort": "none"
        }
      },
      "targets": [
        {
          "datasource": "Prometheus",
          "editorMode": "code",
          "expr": "sum(irate(node_cpu_seconds_total{mode!=\"idle\"}[1m])) by (cpu)",
          "legendFormat": "__auto",
          "range": true,
          "refId": "A"
        }
      ],
      "title": "CPU Usage per cores",
      "type": "timeseries"
    },
    {
      "datasource": "Prometheus",
      "fieldConfig": {
        "defaults": {
          "color": {
            "mode": "palette-classic"
          },
          "custom": {
            "axisCenteredZero": false,
            "axisColorMode": "text",
            "axisLabel": "",
            "axisPlacement": "auto",
            "barAlignment": 0,
            "drawStyle": "line",
            "fillOpacity": 20,
            "gradientMode": "none",
            "hideFrom": {
              "legend": false,
              "tooltip": false,
              "viz": false
            },
            "lineInterpolation": "linear",
            "lineStyle": {
              "fill": "solid"
            },
            "lineWidth": 1,
            "pointSize": 5,
            "scaleDistribution": {
              "type": "linear"
            },
            "showPoints": "never",
            "spanNulls": false,
            "stacking": {
              "group": "A",
              "mode": "none"
            },
            "thresholdsStyle": {
              "mode": "off"
            }
          },
          "mappings": [],
          "min": 0,
          "thresholds": {
            "mode": "absolute",
            "steps": [
              {
                "color": "green",
                "value": null
              }
            ]
          },
          "unit": "bytes"
        },
        "overrides": [
          {
            "matcher": {
              "id": "byName",
              "options": "Used"
            },
            "properties": [
              {
                "id": "custom.stacking",
                "value": {
                  "group": "A",
                  "mode": "normal"
                }
              }
            ]
          },
          {
            "matcher": {
              "id": "byName",
              "options": "Buffer + Cached"
            },
            "properties": [
              {
                "id": "custom.stacking",
                "value": {
                  "group": "A",
                  "mode": "normal"
                }
              }
            ]
          }
        ]
      },
      "gridPos": {
        "h": 9,
        "w": 12,
        "x": 12,
        "y": 23
      },
      "id": 20,
      "options": {
        "legend": {
          "calcs": [],
          "displayMode": "list",
          "placement": "bottom",
          "showLegend": true
        },
        "tooltip": {
          "mode": "single",
          "sort": "none"
        }
      },
      "targets": [
        {
          "datasource": "Prometheus",
          "editorMode": "code",
          "expr": "node_memory_MemTotal_bytes",
          "hide": false,
          "legendFormat": "Total",
          "range": true,
          "refId": "A"
        },
        {
          "datasource": "Prometheus",
          "editorMode": "code",
          "expr": "node_memory_MemTotal_bytes - node_memory_MemFree_bytes - (node_memory_Cached_bytes + node_memory_Buffers_bytes)",
          "legendFormat": "Used",
          "range": true,
          "refId": "B"
        },
        {
          "datasource": "Prometheus",
          "editorMode": "code",
          "expr": "node_memory_Cached_bytes + node_memory_Buffers_bytes",
          "hide": false,
          "legendFormat": "Buffer + Cached",
          "range": true,
          "refId": "C"
        }
      ],
      "title": "Memory Usage",
      "type": "timeseries"
    },
    {
      "datasource": "Prometheus",
      "fieldConfig": {
        "defaults": {
          "color": {
            "mode": "palette-classic"
          },
          "custom": {
            "axisCenteredZero": false,
            "axisColorMode": "text",
            "axisLabel": "",
            "axisPlacement": "auto",
            "barAlignment": 0,
            "drawStyle": "line",
            "fillOpacity": 20,
            "gradientMode": "none",
            "hideFrom": {
              "legend": false,
              "tooltip": false,
              "viz": false
            },
            "lineInterpolation": "linear",
            "lineWidth": 1,
            "pointSize": 5,
            "scaleDistribution": {
              "type": "linear"
            },
            "showPoints": "never",
            "spanNulls": false,
            "stacking": {
              "group": "A",
              "mode": "normal"
            },
            "thresholdsStyle": {
              "mode": "off"
            }
          },
          "mappings": [],
          "min": 0,
          "thresholds": {
            "mode": "absolute",
            "steps": [
              {
                "color": "green",
                "value": null
              }
            ]
          },
          "unit": "s"
        },
        "overrides": []
      },
      "gridPos": {
        "h": 18,
        "w": 12,
        "x": 0,
        "y": 32
      },
      "id": 120,
      "options": {
        "legend": {
          "calcs": [
            "min",
            "mean",
            "max",
            "last"
          ],
          "displayMode": "table",
          "placement": "bottom",
          "showLegend": true
        },
        "tooltip": {
          "mode": "single",
          "sort": "none"
        }
      },
      "targets": [
        {
          "datasource": "Prometheus",
          "editorMode": "code",
          "expr": "sum(irate(node_cpu_seconds_total{mode!=\"idle\"}[1m])) by (mode)",
          "hide": false,
          "legendFormat": "{{mode}}",
          "range": true,
          "refId": "B"
        },
        {
          "datasource": "Prometheus",
          "editorMode": "code",
          "expr": "sum(irate(node_cpu_seconds_total{mode=\"idle\"}[1m])) by (mode)",
          "hide": false,
          "legendFormat": "Idle",
          "range": true,
          "refId": "A"
        }
      ],
      "title": "CPU Usage per mode",
      "type": "timeseries"
    },
    {
      "datasource": "Prometheus",
      "fieldConfig": {
        "defaults": {
          "color": {
            "mode": "palette-classic"
          },
          "custom": {
            "axisCenteredZero": false,
            "axisColorMode": "text",
            "axisLabel": "",
            "axisPlacement": "auto",
            "barAlignment": 0,
            "drawStyle": "line",
            "fillOpacity": 20,
            "gradientMode": "none",
            "hideFrom": {
              "legend": false,
              "tooltip": false,
              "viz": false
            },
            "lineInterpolation": "linear",
            "lineStyle": {
              "fill": "solid"
            },
            "lineWidth": 1,
            "pointSize": 5,
            "scaleDistribution": {
              "type": "linear"
            },
            "showPoints": "never",
            "spanNulls": false,
            "stacking": {
              "group": "A",
              "mode": "normal"
            },
            "thresholdsStyle": {
              "mode": "off"
            }
          },
          "mappings": [],
          "min": 0,
          "thresholds": {
            "mode": "absolute",
            "steps": [
              {
                "color": "green",
                "value": null
              }
            ]
          },
          "unit": "bytes"
        },
        "overrides": []
      },
      "gridPos": {
        "h": 9,
        "w": 6,
        "x": 12,
        "y": 32
      },
      "id": 164,
      "options": {
        "legend": {
          "calcs": [],
          "displayMode": "list",
          "placement": "bottom",
          "showLegend": true
        },
        "tooltip": {
          "mode": "single",
          "sort": "none"
        }
      },
      "targets": [
        {
          "datasource": "Prometheus",
          "editorMode": "code",
          "expr": "node_memory_SReclaimable_bytes",
          "hide": false,
          "legendFormat": "Reclaimable slab cache",
          "range": true,
          "refId": "A"
        },
        {
          "datasource": "Prometheus",
          "editorMode": "code",
          "expr": "node_memory_SUnreclaim_bytes",
          "legendFormat": "Unreclaimable slab cache",
          "range": true,
          "refId": "C"
        },
        {
          "datasource": "Prometheus",
          "editorMode": "code",
          "expr": "node_memory_AnonPages_bytes",
          "hide": false,
          "legendFormat": "Anonymous (Unreclaimable)",
          "range": true,
          "refId": "B"
        },
        {
          "datasource": "Prometheus",
          "editorMode": "code",
          "expr": "node_memory_KernelStack_bytes",
          "hide": false,
          "legendFormat": "KernelStack (Unreclaimable)",
          "range": true,
          "refId": "D"
        },
        {
          "datasource": "Prometheus",
          "editorMode": "code",
          "expr": "node_memory_PageTables_bytes",
          "hide": false,
          "legendFormat": "PageTables (Unreclaimable)",
          "range": true,
          "refId": "E"
        },
        {
          "datasource": "Prometheus",
          "editorMode": "code",
          "expr": "node_memory_VmallocUsed_bytes",
          "hide": false,
          "legendFormat": "VmallocUsed (Unreclaimable)",
          "range": true,
          "refId": "F"
        }
      ],
      "title": "Memory Usage in Used",
      "type": "timeseries"
    },
    {
      "datasource": "Prometheus",
      "description": "",
      "fieldConfig": {
        "defaults": {
          "color": {
            "mode": "palette-classic"
          },
          "custom": {
            "axisCenteredZero": false,
            "axisColorMode": "text",
            "axisLabel": "",
            "axisPlacement": "auto",
            "barAlignment": 0,
            "drawStyle": "line",
            "fillOpacity": 20,
            "gradientMode": "none",
            "hideFrom": {
              "legend": false,
              "tooltip": false,
              "viz": false
            },
            "lineInterpolation": "linear",
            "lineStyle": {
              "fill": "solid"
            },
            "lineWidth": 1,
            "pointSize": 5,
            "scaleDistribution": {
              "type": "linear"
            },
            "showPoints": "never",
            "spanNulls": false,
            "stacking": {
              "group": "A",
              "mode": "none"
            },
            "thresholdsStyle": {
              "mode": "off"
            }
          },
          "mappings": [],
          "min": 0,
          "thresholds": {
            "mode": "absolute",
            "steps": [
              {
                "color": "green",
                "value": null
              }
            ]
          },
          "unit": "bytes"
        },
        "overrides": [
          {
            "matcher": {
              "id": "byName",
              "options": "Unevictable"
            },
            "properties": [
              {
                "id": "color",
                "value": {
                  "fixedColor": "dark-red",
                  "mode": "fixed"
                }
              }
            ]
          },
          {
            "matcher": {
              "id": "byName",
              "options": "Mlocked"
            },
            "properties": [
              {
                "id": "color",
                "value": {
                  "fixedColor": "dark-yellow",
                  "mode": "fixed"
                }
              },
              {
                "id": "custom.stacking",
                "value": {
                  "group": "A",
                  "mode": "normal"
                }
              }
            ]
          }
        ]
      },
      "gridPos": {
        "h": 9,
        "w": 6,
        "x": 18,
        "y": 32
      },
      "id": 186,
      "options": {
        "legend": {
          "calcs": [],
          "displayMode": "list",
          "placement": "bottom",
          "showLegend": true
        },
        "tooltip": {
          "mode": "single",
          "sort": "none"
        }
      },
      "targets": [
        {
          "datasource": "Prometheus",
          "editorMode": "code",
          "expr": "node_memory_Unevictable_bytes",
          "hide": false,
          "interval": "",
          "legendFormat": "Unevictable",
          "range": true,
          "refId": "A"
        },
        {
          "datasource": "Prometheus",
          "editorMode": "code",
          "expr": "node_memory_Mlocked_bytes",
          "legendFormat": "Mlocked",
          "range": true,
          "refId": "C"
        }
      ],
      "title": "Unevictable",
      "type": "timeseries"
    },
    {
      "datasource": "Prometheus",
      "fieldConfig": {
        "defaults": {
          "color": {
            "mode": "palette-classic"
          },
          "custom": {
            "axisCenteredZero": false,
            "axisColorMode": "text",
            "axisLabel": "",
            "axisPlacement": "auto",
            "barAlignment": 0,
            "drawStyle": "line",
            "fillOpacity": 20,
            "gradientMode": "none",
            "hideFrom": {
              "legend": false,
              "tooltip": false,
              "viz": false
            },
            "lineInterpolation": "linear",
            "lineStyle": {
              "fill": "solid"
            },
            "lineWidth": 1,
            "pointSize": 5,
            "scaleDistribution": {
              "type": "linear"
            },
            "showPoints": "never",
            "spanNulls": false,
            "stacking": {
              "group": "A",
              "mode": "normal"
            },
            "thresholdsStyle": {
              "mode": "off"
            }
          },
          "mappings": [],
          "min": 0,
          "thresholds": {
            "mode": "absolute",
            "steps": [
              {
                "color": "green",
                "value": null
              }
            ]
          },
          "unit": "bytes"
        },
        "overrides": []
      },
      "gridPos": {
        "h": 9,
        "w": 6,
        "x": 12,
        "y": 41
      },
      "id": 142,
      "options": {
        "legend": {
          "calcs": [],
          "displayMode": "list",
          "placement": "bottom",
          "showLegend": true
        },
        "tooltip": {
          "mode": "single",
          "sort": "none"
        }
      },
      "targets": [
        {
          "datasource": "Prometheus",
          "editorMode": "code",
          "expr": "node_memory_Inactive_file_bytes",
          "hide": false,
          "legendFormat": "Inactive file cache (Reclaimable)",
          "range": true,
          "refId": "A"
        },
        {
          "datasource": "Prometheus",
          "editorMode": "code",
          "expr": "node_memory_Active_file_bytes",
          "legendFormat": "Active file cache (Reclaimable)",
          "range": true,
          "refId": "C"
        },
        {
          "datasource": "Prometheus",
          "editorMode": "code",
          "expr": "node_memory_Shmem_bytes",
          "hide": false,
          "legendFormat": "Shared (Unreclaimable)",
          "range": true,
          "refId": "D"
        }
      ],
      "title": "Memory Usage in Buffer + Cache",
      "type": "timeseries"
    },
    {
      "datasource": "Prometheus",
      "fieldConfig": {
        "defaults": {
          "color": {
            "mode": "palette-classic"
          },
          "custom": {
            "axisCenteredZero": false,
            "axisColorMode": "text",
            "axisLabel": "",
            "axisPlacement": "auto",
            "barAlignment": 0,
            "drawStyle": "line",
            "fillOpacity": 0,
            "gradientMode": "none",
            "hideFrom": {
              "legend": false,
              "tooltip": false,
              "viz": false
            },
            "lineInterpolation": "linear",
            "lineStyle": {
              "fill": "solid"
            },
            "lineWidth": 1,
            "pointSize": 5,
            "scaleDistribution": {
              "type": "linear"
            },
            "showPoints": "auto",
            "spanNulls": false,
            "stacking": {
              "group": "A",
              "mode": "none"
            },
            "thresholdsStyle": {
              "mode": "off"
            }
          },
          "mappings": [],
          "min": 0,
          "thresholds": {
            "mode": "absolute",
            "steps": [
              {
                "color": "green",
                "value": null
              }
            ]
          },
          "unit": "bytes"
        },
        "overrides": [
          {
            "matcher": {
              "id": "byName",
              "options": "Dirty"
            },
            "properties": [
              {
                "id": "color",
                "value": {
                  "fixedColor": "blue",
                  "mode": "fixed"
                }
              }
            ]
          },
          {
            "matcher": {
              "id": "byName",
              "options": "Writeback"
            },
            "properties": [
              {
                "id": "color",
                "value": {
                  "fixedColor": "orange",
                  "mode": "fixed"
                }
              }
            ]
          }
        ]
      },
      "gridPos": {
        "h": 9,
        "w": 6,
        "x": 18,
        "y": 41
      },
      "id": 184,
      "options": {
        "legend": {
          "calcs": [],
          "displayMode": "list",
          "placement": "bottom",
          "showLegend": true
        },
        "tooltip": {
          "mode": "single",
          "sort": "none"
        }
      },
      "targets": [
        {
          "datasource": "Prometheus",
          "editorMode": "code",
          "expr": "node_memory_Dirty_bytes",
          "hide": false,
          "legendFormat": "Dirty",
          "range": true,
          "refId": "A"
        },
        {
          "datasource": "Prometheus",
          "editorMode": "code",
          "expr": "node_memory_Writeback_bytes",
          "legendFormat": "Writeback",
          "range": true,
          "refId": "C"
        }
      ],
      "title": "Writeback",
      "type": "timeseries"
    },
    {
      "datasource": {
        "type": "prometheus",
        "uid": "PBFA97CFB590B2093"
      },
      "fieldConfig": {
        "defaults": {
          "color": {
            "mode": "palette-classic"
          },
          "custom": {
            "axisCenteredZero": false,
            "axisColorMode": "text",
            "axisLabel": "",
            "axisPlacement": "auto",
            "barAlignment": 0,
            "drawStyle": "line",
            "fillOpacity": 20,
            "gradientMode": "none",
            "hideFrom": {
              "legend": false,
              "tooltip": false,
              "viz": false
            },
            "lineInterpolation": "linear",
            "lineStyle": {
              "fill": "solid"
            },
            "lineWidth": 1,
            "pointSize": 5,
            "scaleDistribution": {
              "type": "linear"
            },
            "showPoints": "never",
            "spanNulls": false,
            "stacking": {
              "group": "A",
              "mode": "none"
            },
            "thresholdsStyle": {
              "mode": "off"
            }
          },
          "mappings": [],
          "min": 0,
          "thresholds": {
            "mode": "absolute",
            "steps": [
              {
                "color": "green",
                "value": null
              }
            ]
          },
          "unit": "bytes"
        },
        "overrides": [
          {
            "matcher": {
              "id": "byName",
              "options": "Used"
            },
            "properties": [
              {
                "id": "custom.stacking",
                "value": {
                  "group": "A",
                  "mode": "normal"
                }
              }
            ]
          },
          {
            "matcher": {
              "id": "byName",
              "options": "Buffer + Cached"
            },
            "properties": [
              {
                "id": "custom.stacking",
                "value": {
                  "group": "A",
                  "mode": "normal"
                }
              }
            ]
          }
        ]
      },
      "gridPos": {
        "h": 9,
        "w": 12,
        "x": 0,
        "y": 50
      },
      "id": 243,
      "options": {
        "legend": {
          "calcs": [],
          "displayMode": "list",
          "placement": "bottom",
          "showLegend": true
        },
        "tooltip": {
          "mode": "single",
          "sort": "none"
        }
      },
      "targets": [
        {
          "datasource": "Prometheus",
          "editorMode": "code",
          "expr": "(DCGM_FI_DEV_FB_USED + DCGM_FI_DEV_FB_FREE) * 1024 * 1024",
          "hide": false,
          "legendFormat": "Total",
          "range": true,
          "refId": "A"
        },
        {
          "datasource": "Prometheus",
          "editorMode": "code",
          "expr": "DCGM_FI_DEV_FB_USED * 1024 * 1024",
          "legendFormat": "Used",
          "range": true,
          "refId": "B"
        }
      ],
      "title": "GPU Memory Usage",
      "type": "timeseries"
    },
    {
      "datasource": {
        "type": "prometheus",
        "uid": "PBFA97CFB590B2093"
      },
      "fieldConfig": {
        "defaults": {
          "color": {
            "mode": "palette-classic"
          },
          "custom": {
            "axisCenteredZero": false,
            "axisColorMode": "text",
            "axisLabel": "",
            "axisPlacement": "auto",
            "barAlignment": 0,
            "drawStyle": "line",
            "fillOpacity": 0,
            "gradientMode": "none",
            "hideFrom": {
              "legend": false,
              "tooltip": false,
              "viz": false
            },
            "lineInterpolation": "smooth",
            "lineWidth": 1,
            "pointSize": 5,
            "scaleDistribution": {
              "type": "linear"
            },
            "showPoints": "auto",
            "spanNulls": false,
            "stacking": {
              "group": "A",
              "mode": "none"
            },
            "thresholdsStyle": {
              "mode": "off"
            }
          },
          "mappings": [],
          "thresholds": {
            "mode": "absolute",
            "steps": [
              {
                "color": "green",
                "value": null
              },
              {
                "color": "red",
                "value": 80
              }
            ]
          },
          "unit": "celsius"
        },
        "overrides": []
      },
      "gridPos": {
        "h": 9,
        "w": 12,
        "x": 12,
        "y": 50
      },
      "id": 242,
      "options": {
        "legend": {
          "calcs": [],
          "displayMode": "list",
          "placement": "bottom",
          "showLegend": true
        },
        "tooltip": {
          "mode": "single",
          "sort": "none"
        }
      },
      "targets": [
        {
          "datasource": "Prometheus",
          "editorMode": "code",
          "expr": "sum(DCGM_FI_DEV_GPU_TEMP) by (modelName)",
          "legendFormat": "__auto",
          "range": true,
          "refId": "A"
        }
      ],
      "title": "GPU Temp",
      "type": "timeseries"
    },
    {
      "datasource": "Prometheus",
      "description": "",
      "fieldConfig": {
        "defaults": {
          "color": {
            "mode": "palette-classic"
          },
          "custom": {
            "axisCenteredZero": false,
            "axisColorMode": "text",
            "axisLabel": "",
            "axisPlacement": "auto",
            "barAlignment": 0,
            "drawStyle": "line",
            "fillOpacity": 0,
            "gradientMode": "none",
            "hideFrom": {
              "legend": false,
              "tooltip": false,
              "viz": false
            },
            "lineInterpolation": "linear",
            "lineWidth": 1,
            "pointSize": 5,
            "scaleDistribution": {
              "type": "linear"
            },
            "showPoints": "auto",
            "spanNulls": false,
            "stacking": {
              "group": "A",
              "mode": "none"
            },
            "thresholdsStyle": {
              "mode": "off"
            }
          },
          "mappings": [],
          "min": 0,
          "thresholds": {
            "mode": "absolute",
            "steps": [
              {
                "color": "green",
                "value": null
              }
            ]
          },
          "unit": "s"
        },
        "overrides": []
      },
      "gridPos": {
        "h": 8,
        "w": 8,
        "x": 0,
        "y": 59
      },
      "id": 206,
      "options": {
        "legend": {
          "calcs": [],
          "displayMode": "list",
          "placement": "bottom",
          "showLegend": true
        },
        "tooltip": {
          "mode": "single",
          "sort": "none"
        }
      },
      "targets": [
        {
          "datasource": "Prometheus",
          "editorMode": "code",
          "expr": "sum(irate(node_pressure_cpu_waiting_seconds_total[1m]))",
          "legendFormat": "Waiting",
          "range": true,
          "refId": "A"
        }
      ],
      "title": "CPU Pressures",
      "type": "timeseries"
    },
    {
      "datasource": "Prometheus",
      "description": "",
      "fieldConfig": {
        "defaults": {
          "color": {
            "mode": "palette-classic"
          },
          "custom": {
            "axisCenteredZero": false,
            "axisColorMode": "text",
            "axisLabel": "",
            "axisPlacement": "auto",
            "barAlignment": 0,
            "drawStyle": "line",
            "fillOpacity": 0,
            "gradientMode": "none",
            "hideFrom": {
              "legend": false,
              "tooltip": false,
              "viz": false
            },
            "lineInterpolation": "linear",
            "lineWidth": 1,
            "pointSize": 5,
            "scaleDistribution": {
              "type": "linear"
            },
            "showPoints": "auto",
            "spanNulls": false,
            "stacking": {
              "group": "A",
              "mode": "none"
            },
            "thresholdsStyle": {
              "mode": "off"
            }
          },
          "mappings": [],
          "min": 0,
          "thresholds": {
            "mode": "absolute",
            "steps": [
              {
                "color": "green",
                "value": null
              }
            ]
          },
          "unit": "s"
        },
        "overrides": []
      },
      "gridPos": {
        "h": 8,
        "w": 8,
        "x": 8,
        "y": 59
      },
      "id": 208,
      "options": {
        "legend": {
          "calcs": [],
          "displayMode": "list",
          "placement": "bottom",
          "showLegend": true
        },
        "tooltip": {
          "mode": "single",
          "sort": "none"
        }
      },
      "targets": [
        {
          "datasource": "Prometheus",
          "editorMode": "code",
          "expr": "sum(irate(node_pressure_memory_waiting_seconds_total[1m]))",
          "legendFormat": "Waiting",
          "range": true,
          "refId": "A"
        },
        {
          "datasource": "Prometheus",
          "editorMode": "code",
          "expr": "sum(irate(node_pressure_memory_stalled_seconds_total[1m]))",
          "hide": false,
          "legendFormat": "Stalled",
          "range": true,
          "refId": "B"
        }
      ],
      "title": "Memory Pressures",
      "type": "timeseries"
    },
    {
      "datasource": "Prometheus",
      "description": "",
      "fieldConfig": {
        "defaults": {
          "color": {
            "mode": "palette-classic"
          },
          "custom": {
            "axisCenteredZero": false,
            "axisColorMode": "text",
            "axisLabel": "",
            "axisPlacement": "auto",
            "barAlignment": 0,
            "drawStyle": "line",
            "fillOpacity": 0,
            "gradientMode": "none",
            "hideFrom": {
              "legend": false,
              "tooltip": false,
              "viz": false
            },
            "lineInterpolation": "linear",
            "lineWidth": 1,
            "pointSize": 5,
            "scaleDistribution": {
              "type": "linear"
            },
            "showPoints": "auto",
            "spanNulls": false,
            "stacking": {
              "group": "A",
              "mode": "none"
            },
            "thresholdsStyle": {
              "mode": "off"
            }
          },
          "mappings": [],
          "min": 0,
          "thresholds": {
            "mode": "absolute",
            "steps": [
              {
                "color": "green",
                "value": null
              }
            ]
          },
          "unit": "s"
        },
        "overrides": []
      },
      "gridPos": {
        "h": 8,
        "w": 8,
        "x": 16,
        "y": 59
      },
      "id": 210,
      "options": {
        "legend": {
          "calcs": [],
          "displayMode": "list",
          "placement": "bottom",
          "showLegend": true
        },
        "tooltip": {
          "mode": "single",
          "sort": "none"
        }
      },
      "targets": [
        {
          "datasource": "Prometheus",
          "editorMode": "code",
          "expr": "sum(irate(node_pressure_io_waiting_seconds_total[1m]))",
          "hide": false,
          "legendFormat": "Waiting",
          "range": true,
          "refId": "A"
        },
        {
          "datasource": "Prometheus",
          "editorMode": "code",
          "expr": "sum(irate(node_pressure_io_stalled_seconds_total[1m]))",
          "hide": false,
          "legendFormat": "Stalled",
          "range": true,
          "refId": "B"
        }
      ],
      "title": "IO Pressures",
      "type": "timeseries"
    },
    {
      "datasource": "Prometheus",
      "fieldConfig": {
        "defaults": {
          "color": {
            "mode": "palette-classic"
          },
          "custom": {
            "axisCenteredZero": false,
            "axisColorMode": "text",
            "axisLabel": "",
            "axisPlacement": "auto",
            "barAlignment": 0,
            "drawStyle": "line",
            "fillOpacity": 20,
            "gradientMode": "none",
            "hideFrom": {
              "legend": false,
              "tooltip": false,
              "viz": false
            },
            "lineInterpolation": "smooth",
            "lineWidth": 1,
            "pointSize": 5,
            "scaleDistribution": {
              "type": "linear"
            },
            "showPoints": "never",
            "spanNulls": false,
            "stacking": {
              "group": "A",
              "mode": "none"
            },
            "thresholdsStyle": {
              "mode": "off"
            }
          },
          "mappings": [],
          "thresholds": {
            "mode": "absolute",
            "steps": [
              {
                "color": "green",
                "value": null
              }
            ]
          },
          "unit": "binbps"
        },
        "overrides": [
          {
            "matcher": {
              "id": "byName",
              "options": "Transmit"
            },
            "properties": [
              {
                "id": "custom.transform",
                "value": "negative-Y"
              }
            ]
          }
        ]
      },
      "gridPos": {
        "h": 8,
        "w": 12,
        "x": 0,
        "y": 67
      },
      "id": 22,
      "maxPerRow": 6,
      "options": {
        "legend": {
          "calcs": [],
          "displayMode": "list",
          "placement": "bottom",
          "showLegend": true
        },
        "tooltip": {
          "mode": "single",
          "sort": "none"
        }
      },
      "repeat": "NetworkDevice",
      "repeatDirection": "h",
      "targets": [
        {
          "datasource": "Prometheus",
          "editorMode": "code",
          "expr": "sum(irate(node_network_receive_bytes_total{device=\"$NetworkDevice\"}[1m])*8)",
          "legendFormat": "Receive",
          "range": true,
          "refId": "A"
        },
        {
          "datasource": "Prometheus",
          "editorMode": "code",
          "expr": "sum(irate(node_network_transmit_bytes_total{device=\"$NetworkDevice\"}[1m])*8)",
          "hide": false,
          "legendFormat": "Transmit",
          "range": true,
          "refId": "B"
        }
      ],
      "title": "Network Device ($NetworkDevice) Usage",
      "transformations": [],
      "type": "timeseries"
    },
    {
      "datasource": "Prometheus",
      "fieldConfig": {
        "defaults": {
          "color": {
            "mode": "palette-classic"
          },
          "custom": {
            "axisCenteredZero": false,
            "axisColorMode": "text",
            "axisLabel": "",
            "axisPlacement": "auto",
            "barAlignment": 0,
            "drawStyle": "line",
            "fillOpacity": 20,
            "gradientMode": "none",
            "hideFrom": {
              "legend": false,
              "tooltip": false,
              "viz": false
            },
            "lineInterpolation": "smooth",
            "lineWidth": 1,
            "pointSize": 5,
            "scaleDistribution": {
              "type": "linear"
            },
            "showPoints": "never",
            "spanNulls": false,
            "stacking": {
              "group": "A",
              "mode": "none"
            },
            "thresholdsStyle": {
              "mode": "off"
            }
          },
          "mappings": [],
          "thresholds": {
            "mode": "absolute",
            "steps": [
              {
                "color": "green",
                "value": null
              }
            ]
          },
          "unit": "pps"
        },
        "overrides": [
          {
            "matcher": {
              "id": "byName",
              "options": "Receive"
            },
            "properties": [
              {
                "id": "color",
                "value": {
                  "fixedColor": "blue",
                  "mode": "fixed"
                }
              }
            ]
          },
          {
            "matcher": {
              "id": "byName",
              "options": "Transmit"
            },
            "properties": [
              {
                "id": "color",
                "value": {
                  "fixedColor": "orange",
                  "mode": "fixed"
                }
              },
              {
                "id": "custom.transform",
                "value": "negative-Y"
              }
            ]
          }
        ]
      },
      "gridPos": {
        "h": 8,
        "w": 12,
        "x": 0,
        "y": 75
      },
      "id": 35,
      "maxPerRow": 6,
      "options": {
        "legend": {
          "calcs": [],
          "displayMode": "list",
          "placement": "bottom",
          "showLegend": true
        },
        "tooltip": {
          "mode": "single",
          "sort": "none"
        }
      },
      "repeat": "NetworkDevice",
      "repeatDirection": "h",
      "targets": [
        {
          "datasource": "Prometheus",
          "editorMode": "code",
          "expr": "sum(irate(node_network_receive_packets_total{device=\"$NetworkDevice\"}[1m])*8)",
          "legendFormat": "Receive",
          "range": true,
          "refId": "A"
        },
        {
          "datasource": "Prometheus",
          "editorMode": "code",
          "expr": "sum(irate(node_network_transmit_packets_total{device=\"$NetworkDevice\"}[1m])*8)",
          "hide": false,
          "legendFormat": "Transmit",
          "range": true,
          "refId": "B"
        }
      ],
      "title": "Network Device ($NetworkDevice) Packets",
      "transformations": [],
      "type": "timeseries"
    },
    {
      "datasource": "Prometheus",
      "fieldConfig": {
        "defaults": {
          "color": {
            "mode": "palette-classic"
          },
          "custom": {
            "axisCenteredZero": false,
            "axisColorMode": "text",
            "axisLabel": "",
            "axisPlacement": "auto",
            "barAlignment": 0,
            "drawStyle": "line",
            "fillOpacity": 20,
            "gradientMode": "none",
            "hideFrom": {
              "legend": false,
              "tooltip": false,
              "viz": false
            },
            "lineInterpolation": "smooth",
            "lineWidth": 1,
            "pointSize": 5,
            "scaleDistribution": {
              "type": "linear"
            },
            "showPoints": "never",
            "spanNulls": false,
            "stacking": {
              "group": "A",
              "mode": "none"
            },
            "thresholdsStyle": {
              "mode": "off"
            }
          },
          "mappings": [],
          "thresholds": {
            "mode": "absolute",
            "steps": [
              {
                "color": "green"
              }
            ]
          },
          "unit": "pps"
        },
        "overrides": [
          {
            "matcher": {
              "id": "byName",
              "options": "Receive"
            },
            "properties": [
              {
                "id": "color",
                "value": {
                  "fixedColor": "purple",
                  "mode": "fixed"
                }
              }
            ]
          },
          {
            "matcher": {
              "id": "byName",
              "options": "Transmit"
            },
            "properties": [
              {
                "id": "color",
                "value": {
                  "fixedColor": "red",
                  "mode": "fixed"
                }
              },
              {
                "id": "custom.transform",
                "value": "negative-Y"
              }
            ]
          }
        ]
      },
      "gridPos": {
        "h": 8,
        "w": 12,
        "x": 0,
        "y": 83
      },
      "id": 46,
      "maxPerRow": 6,
      "options": {
        "legend": {
          "calcs": [],
          "displayMode": "list",
          "placement": "bottom",
          "showLegend": true
        },
        "tooltip": {
          "mode": "single",
          "sort": "none"
        }
      },
      "repeat": "NetworkDevice",
      "repeatDirection": "h",
      "targets": [
        {
          "datasource": "Prometheus",
          "editorMode": "code",
          "expr": "sum(irate(node_network_receive_drop_total{device=\"$NetworkDevice\"}[1m])*8)",
          "legendFormat": "Receive",
          "range": true,
          "refId": "A"
        },
        {
          "datasource": "Prometheus",
          "editorMode": "code",
          "expr": "sum(irate(node_network_transmit_drop_total{device=\"$NetworkDevice\"}[1m])*8)",
          "hide": false,
          "legendFormat": "Transmit",
          "range": true,
          "refId": "B"
        }
      ],
      "title": "Network Device ($NetworkDevice) Dropped Packets",
      "transformations": [],
      "type": "timeseries"
    },
    {
      "datasource": "Prometheus",
      "fieldConfig": {
        "defaults": {
          "color": {
            "mode": "palette-classic"
          },
          "custom": {
            "axisCenteredZero": false,
            "axisColorMode": "text",
            "axisLabel": "",
            "axisPlacement": "auto",
            "barAlignment": 0,
            "drawStyle": "line",
            "fillOpacity": 0,
            "gradientMode": "none",
            "hideFrom": {
              "legend": false,
              "tooltip": false,
              "viz": false
            },
            "lineInterpolation": "linear",
            "lineWidth": 1,
            "pointSize": 5,
            "scaleDistribution": {
              "type": "linear"
            },
            "showPoints": "auto",
            "spanNulls": false,
            "stacking": {
              "group": "A",
              "mode": "none"
            },
            "thresholdsStyle": {
              "mode": "off"
            }
          },
          "mappings": [],
          "thresholds": {
            "mode": "absolute",
            "steps": [
              {
                "color": "green"
              }
            ]
          },
          "unit": "pps"
        },
        "overrides": [
          {
            "matcher": {
              "id": "byName",
              "options": "Segments Retransmission"
            },
            "properties": [
              {
                "id": "color",
                "value": {
                  "fixedColor": "dark-red",
                  "mode": "fixed"
                }
              }
            ]
          },
          {
            "matcher": {
              "id": "byName",
              "options": "SYN Retransmission"
            },
            "properties": [
              {
                "id": "color",
                "value": {
                  "fixedColor": "dark-yellow",
                  "mode": "fixed"
                }
              },
              {
                "id": "custom.stacking",
                "value": {
                  "group": "A",
                  "mode": "normal"
                }
              }
            ]
          }
        ]
      },
      "gridPos": {
        "h": 5,
        "w": 12,
        "x": 0,
        "y": 91
      },
      "id": 79,
      "options": {
        "legend": {
          "calcs": [],
          "displayMode": "list",
          "placement": "bottom",
          "showLegend": true
        },
        "tooltip": {
          "mode": "single",
          "sort": "none"
        }
      },
      "pluginVersion": "9.1.6",
      "targets": [
        {
          "datasource": "Prometheus",
          "editorMode": "code",
          "expr": "sum(irate(node_netstat_Tcp_RetransSegs[1m]))",
          "legendFormat": "Segments Retransmission",
          "range": true,
          "refId": "A"
        },
        {
          "datasource": "Prometheus",
          "editorMode": "code",
          "expr": "sum(irate(node_netstat_TcpExt_TCPSynRetrans[1m]))",
          "hide": false,
          "legendFormat": "SYN Retransmission",
          "range": true,
          "refId": "B"
        }
      ],
      "title": "TCP Retransmission",
      "type": "timeseries"
    },
    {
      "datasource": "Prometheus",
      "fieldConfig": {
        "defaults": {
          "color": {
            "mode": "palette-classic"
          },
          "custom": {
            "axisCenteredZero": false,
            "axisColorMode": "text",
            "axisLabel": "",
            "axisPlacement": "auto",
            "barAlignment": 0,
            "drawStyle": "line",
            "fillOpacity": 0,
            "gradientMode": "none",
            "hideFrom": {
              "legend": false,
              "tooltip": false,
              "viz": false
            },
            "lineInterpolation": "linear",
            "lineWidth": 1,
            "pointSize": 5,
            "scaleDistribution": {
              "type": "linear"
            },
            "showPoints": "auto",
            "spanNulls": false,
            "stacking": {
              "group": "A",
              "mode": "none"
            },
            "thresholdsStyle": {
              "mode": "off"
            }
          },
          "mappings": [],
          "thresholds": {
            "mode": "absolute",
            "steps": [
              {
                "color": "green"
              }
            ]
          },
          "unit": "pps"
        },
        "overrides": [
          {
            "matcher": {
              "id": "byName",
              "options": "Timeouts"
            },
            "properties": [
              {
                "id": "color",
                "value": {
                  "fixedColor": "dark-red",
                  "mode": "fixed"
                }
              }
            ]
          }
        ]
      },
      "gridPos": {
        "h": 5,
        "w": 12,
        "x": 12,
        "y": 91
      },
      "id": 81,
      "options": {
        "legend": {
          "calcs": [],
          "displayMode": "list",
          "placement": "bottom",
          "showLegend": true
        },
        "tooltip": {
          "mode": "single",
          "sort": "none"
        }
      },
      "pluginVersion": "9.1.6",
      "targets": [
        {
          "datasource": "Prometheus",
          "editorMode": "code",
          "expr": "sum(irate(node_netstat_TcpExt_TCPTimeouts[1m]))",
          "legendFormat": "Timeouts",
          "range": true,
          "refId": "A"
        }
      ],
      "title": "TCP Retransmission Timeouts",
      "type": "timeseries"
    },
    {
      "datasource": "Prometheus",
      "fieldConfig": {
        "defaults": {
          "color": {
            "mode": "palette-classic"
          },
          "custom": {
            "axisCenteredZero": false,
            "axisColorMode": "text",
            "axisLabel": "",
            "axisPlacement": "auto",
            "barAlignment": 0,
            "drawStyle": "line",
            "fillOpacity": 20,
            "gradientMode": "none",
            "hideFrom": {
              "legend": false,
              "tooltip": false,
              "viz": false
            },
            "lineInterpolation": "smooth",
            "lineWidth": 1,
            "pointSize": 5,
            "scaleDistribution": {
              "type": "linear"
            },
            "showPoints": "never",
            "spanNulls": false,
            "stacking": {
              "group": "A",
              "mode": "none"
            },
            "thresholdsStyle": {
              "mode": "off"
            }
          },
          "mappings": [],
          "thresholds": {
            "mode": "absolute",
            "steps": [
              {
                "color": "green"
              }
            ]
          },
          "unit": "binBps"
        },
        "overrides": [
          {
            "matcher": {
              "id": "byName",
              "options": "Write"
            },
            "properties": [
              {
                "id": "custom.transform",
                "value": "negative-Y"
              }
            ]
          }
        ]
      },
      "gridPos": {
        "h": 8,
        "w": 24,
        "x": 0,
        "y": 96
      },
      "id": 28,
      "maxPerRow": 6,
      "options": {
        "legend": {
          "calcs": [],
          "displayMode": "list",
          "placement": "bottom",
          "showLegend": true
        },
        "tooltip": {
          "mode": "single",
          "sort": "none"
        }
      },
      "repeat": "DiskDevice",
      "repeatDirection": "h",
      "targets": [
        {
          "datasource": "Prometheus",
          "editorMode": "code",
          "expr": "sum(irate(node_disk_read_bytes_total{device=\"$DiskDevice\"}[1m]))",
          "legendFormat": "Read",
          "range": true,
          "refId": "A"
        },
        {
          "datasource": "Prometheus",
          "editorMode": "code",
          "expr": "sum(irate(node_disk_written_bytes_total{device=\"$DiskDevice\"}[1m]))",
          "hide": false,
          "legendFormat": "Write",
          "range": true,
          "refId": "B"
        }
      ],
      "title": "Disk ($DiskDevice) Usage",
      "transformations": [],
      "type": "timeseries"
    },
    {
      "datasource": "Prometheus",
      "fieldConfig": {
        "defaults": {
          "color": {
            "mode": "palette-classic"
          },
          "custom": {
            "axisCenteredZero": false,
            "axisColorMode": "text",
            "axisLabel": "",
            "axisPlacement": "auto",
            "barAlignment": 0,
            "drawStyle": "line",
            "fillOpacity": 20,
            "gradientMode": "none",
            "hideFrom": {
              "legend": false,
              "tooltip": false,
              "viz": false
            },
            "lineInterpolation": "smooth",
            "lineWidth": 1,
            "pointSize": 5,
            "scaleDistribution": {
              "type": "linear"
            },
            "showPoints": "never",
            "spanNulls": false,
            "stacking": {
              "group": "A",
              "mode": "none"
            },
            "thresholdsStyle": {
              "mode": "off"
            }
          },
          "mappings": [],
          "thresholds": {
            "mode": "absolute",
            "steps": [
              {
                "color": "green"
              }
            ]
          },
          "unit": "iops"
        },
        "overrides": [
          {
            "matcher": {
              "id": "byName",
              "options": "Read"
            },
            "properties": [
              {
                "id": "color",
                "value": {
                  "fixedColor": "blue",
                  "mode": "fixed"
                }
              }
            ]
          },
          {
            "matcher": {
              "id": "byName",
              "options": "Write"
            },
            "properties": [
              {
                "id": "color",
                "value": {
                  "fixedColor": "orange",
                  "mode": "fixed"
                }
              },
              {
                "id": "custom.transform",
                "value": "negative-Y"
              }
            ]
          }
        ]
      },
      "gridPos": {
        "h": 8,
        "w": 24,
        "x": 0,
        "y": 104
      },
      "id": 63,
      "maxPerRow": 6,
      "options": {
        "legend": {
          "calcs": [],
          "displayMode": "list",
          "placement": "bottom",
          "showLegend": true
        },
        "tooltip": {
          "mode": "single",
          "sort": "none"
        }
      },
      "repeat": "DiskDevice",
      "repeatDirection": "h",
      "targets": [
        {
          "datasource": "Prometheus",
          "editorMode": "code",
          "expr": "sum(irate(node_disk_reads_completed_total{device=\"$DiskDevice\"}[1m]))",
          "legendFormat": "Read",
          "range": true,
          "refId": "A"
        },
        {
          "datasource": "Prometheus",
          "editorMode": "code",
          "expr": "sum(irate(node_disk_writes_completed_total{device=\"$DiskDevice\"}[1m]))",
          "hide": false,
          "legendFormat": "Write",
          "range": true,
          "refId": "B"
        }
      ],
      "title": "Disk ($DiskDevice) IOps",
      "transformations": [],
      "type": "timeseries"
    },
    {
      "datasource": "Prometheus",
      "fieldConfig": {
        "defaults": {
          "color": {
            "mode": "palette-classic"
          },
          "custom": {
            "axisCenteredZero": false,
            "axisColorMode": "text",
            "axisLabel": "",
            "axisPlacement": "auto",
            "barAlignment": 0,
            "drawStyle": "line",
            "fillOpacity": 20,
            "gradientMode": "none",
            "hideFrom": {
              "legend": false,
              "tooltip": false,
              "viz": false
            },
            "lineInterpolation": "smooth",
            "lineWidth": 1,
            "pointSize": 5,
            "scaleDistribution": {
              "type": "linear"
            },
            "showPoints": "never",
            "spanNulls": false,
            "stacking": {
              "group": "A",
              "mode": "none"
            },
            "thresholdsStyle": {
              "mode": "off"
            }
          },
          "mappings": [],
          "thresholds": {
            "mode": "absolute",
            "steps": [
              {
                "color": "green"
              }
            ]
          },
          "unit": "s"
        },
        "overrides": [
          {
            "matcher": {
              "id": "byName",
              "options": "Read"
            },
            "properties": [
              {
                "id": "color",
                "value": {
                  "fixedColor": "dark-blue",
                  "mode": "fixed"
                }
              }
            ]
          },
          {
            "matcher": {
              "id": "byName",
              "options": "Write"
            },
            "properties": [
              {
                "id": "color",
                "value": {
                  "fixedColor": "dark-orange",
                  "mode": "fixed"
                }
              },
              {
                "id": "custom.transform",
                "value": "negative-Y"
              }
            ]
          }
        ]
      },
      "gridPos": {
        "h": 8,
        "w": 24,
        "x": 0,
        "y": 112
      },
      "id": 100,
      "maxPerRow": 6,
      "options": {
        "legend": {
          "calcs": [],
          "displayMode": "list",
          "placement": "bottom",
          "showLegend": true
        },
        "tooltip": {
          "mode": "single",
          "sort": "none"
        }
      },
      "repeat": "DiskDevice",
      "repeatDirection": "h",
      "targets": [
        {
          "datasource": "Prometheus",
          "editorMode": "code",
          "expr": "sum(irate(node_disk_read_time_seconds_total{device=\"$DiskDevice\"}[1m]) / irate(node_disk_reads_completed_total{device=\"$DiskDevice\"}[1m]))",
          "legendFormat": "Read",
          "range": true,
          "refId": "A"
        },
        {
          "datasource": "Prometheus",
          "editorMode": "code",
          "expr": "sum(irate(node_disk_write_time_seconds_total{device=\"$DiskDevice\"}[1m]) / irate(node_disk_writes_completed_total{device=\"$DiskDevice\"}[1m]))",
          "hide": false,
          "legendFormat": "Write",
          "range": true,
          "refId": "B"
        }
      ],
      "title": "Disk ($DiskDevice) Latency",
      "transformations": [],
      "type": "timeseries"
    }
  ],
  "refresh": "5s",
  "schemaVersion": 38,
  "style": "dark",
  "tags": [],
  "templating": {
    "list": [
      {
        "current": {
          "selected": false,
          "text": "All",
          "value": "$__all"
        },
        "datasource": {
          "type": "prometheus",
          "uid": "PBFA97CFB590B2093"
        },
        "definition": "label_values(node_network_transmit_bytes_total, device)",
        "hide": 2,
        "includeAll": true,
        "multi": false,
        "name": "NetworkDevice",
        "options": [],
        "query": {
          "query": "label_values(node_network_transmit_bytes_total, device)",
          "refId": "StandardVariableQuery"
        },
        "refresh": 1,
        "regex": "",
        "skipUrlSync": false,
        "sort": 0,
        "type": "query"
      },
      {
        "current": {
          "selected": false,
          "text": "All",
          "value": "$__all"
        },
        "datasource": {
          "type": "prometheus",
          "uid": "PBFA97CFB590B2093"
        },
        "definition": "label_values(node_disk_info{device!~\"dm-.*\"}, device)",
        "hide": 2,
        "includeAll": true,
        "multi": false,
        "name": "DiskDevice",
        "options": [],
        "query": {
          "query": "label_values(node_disk_info{device!~\"dm-.*\"}, device)",
          "refId": "StandardVariableQuery"
        },
        "refresh": 1,
        "regex": "",
        "skipUrlSync": false,
        "sort": 0,
        "type": "query"
      }
    ]
  },
  "time": {
    "from": "now-15m",
    "to": "now"
  },
  "timepicker": {},
  "timezone": "",
  "title": "Overview",
  "uid": "vJ2bZ0I4k",
  "version": 1,
  "weekStart": ""
}
